idf_ci/__init__.py
idf_ci/_compat.py
idf_ci/_vendor.py
idf_ci/envs.py
idf_ci/scripts.py
idf_ci/settings.py
idf_ci/utils.py
idf_ci/build_collect/scripts.py
idf_ci/build_collect/template.html
idf_ci/cli/__init__.py
idf_ci/cli/_options.py
idf_ci/cli/build_group.py
idf_ci/cli/gitlab_group.py
idf_ci/cli/test_group.py
idf_ci/idf_gitlab/__init__.py
idf_ci/idf_gitlab/api.py
idf_ci/idf_gitlab/pipeline.py
idf_ci/idf_gitlab/scripts.py
idf_ci/idf_pytest/__init__.py
idf_ci/idf_pytest/models.py
idf_ci/idf_pytest/plugin.py
idf_ci/idf_pytest/scripts.py
idf_ci/templates/.idf_build_apps.toml
idf_ci/templates/.idf_ci.toml
idf_ci/templates/__init__.py
idf_ci/templates/pytest.ini
idf_ci-0.6.0.dist-info/METADATA
idf_ci-0.6.0.dist-info/WHEEL
idf_ci-0.6.0.dist-info/entry_points.txt
idf_ci-0.6.0.dist-info/top_level.txt
idf_ci-0.6.0.dist-info/RECORD
