Metadata-Version: 2.4
Name: idf-ci
Version: 0.6.0
Summary: The python library for CI/CD of ESP-IDF projects
Author-email: Fu Hanxi <fuhanxi@espressif.com>
Project-URL: Homepage, https://github.com/espressif/idf-ci
Project-URL: Documentation, https://docs.espressif.com/projects/idf-ci
Project-URL: Repository, https://github.com/espressif/idf-ci.git
Project-URL: Changelog, https://github.com/espressif/idf-ci/blob/master/CHANGELOG.md
Classifier: Development Status :: 4 - Beta
Classifier: Intended Audience :: Developers
Classifier: License :: OSI Approved :: Apache Software License
Classifier: Programming Language :: Python :: 3
Classifier: Programming Language :: Python :: 3.7
Classifier: Programming Language :: Python :: 3.8
Classifier: Programming Language :: Python :: 3.9
Classifier: Programming Language :: Python :: 3.10
Classifier: Programming Language :: Python :: 3.11
Classifier: Programming Language :: Python :: 3.12
Classifier: Programming Language :: Python :: 3.13
Classifier: Topic :: Software Development :: Testing
Requires-Python: >=3.7
Requires-Dist: click
Requires-Dist: tomlkit
Requires-Dist: pyyaml
Requires-Dist: jinja2
Requires-Dist: python-gitlab
Requires-Dist: minio
Requires-Dist: idf-build-apps<3,>=2.12.3
Requires-Dist: pytest-embedded-idf[serial]<3,>=1.16
Requires-Dist: pytest-embedded-jtag<3,>=1.16
Requires-Dist: pytest-embedded-qemu<3,>=1.16
Requires-Dist: pytest-ignore-test-results<1,>=0.3.0
Requires-Dist: pytest-timeout
Requires-Dist: pytest-rerunfailures
Requires-Dist: rich
Requires-Dist: typing-extensions; python_version < "3.11"
Provides-Extra: test
Requires-Dist: pytest; extra == "test"
Requires-Dist: pytest-cov; extra == "test"
Requires-Dist: beautifulsoup4; extra == "test"
Provides-Extra: doc
Requires-Dist: sphinx; extra == "doc"
Requires-Dist: sphinx-rtd-theme; extra == "doc"
Requires-Dist: sphinx_copybutton; extra == "doc"
Requires-Dist: myst-parser; extra == "doc"
Requires-Dist: sphinxcontrib-mermaid; extra == "doc"
Requires-Dist: sphinx-argparse; extra == "doc"
Requires-Dist: sphinx-tabs; extra == "doc"
Requires-Dist: autodoc-pydantic; extra == "doc"
